anguilla/__init__.py
anguilla/__main__.py
anguilla/__version__.py
anguilla/app/__init__.py
anguilla/app/server.py
anguilla/embed.py
anguilla/interpolate.py
anguilla/nnsearch.py
anguilla/serialize.py
anguilla/types.py
anguilla_iml-0.3.0.dist-info/LICENSE
anguilla_iml-0.3.0.dist-info/METADATA
anguilla_iml-0.3.0.dist-info/WHEEL
anguilla_iml-0.3.0.dist-info/entry_points.txt
anguilla_iml-0.3.0.dist-info/RECORD
