Metadata-Version: 2.1
Name: anguilla-iml
Version: 0.3.0
Summary: a package for interactive machine learning
License: MIT
Author: Victor Shepardson
Author-email: victor.shepardson@gmail.com
Requires-Python: >=3.10,<3.13
Classifier: License :: OSI Approved :: MIT License
Classifier: Programming Language :: Python :: 3
Classifier: Programming Language :: Python :: 3.10
Classifier: Programming Language :: Python :: 3.11
Classifier: Programming Language :: Python :: 3.12
Provides-Extra: torch
Requires-Dist: faiss-cpu (>=1.7,<2.0)
Requires-Dist: iipyper (>=0.1.7,<0.2.0)
Requires-Dist: numpy (>=1.23,<2.0)
Requires-Dist: scipy (>=1.13.1,<2.0.0)
Requires-Dist: torch (>=2.1.0,<2.2.0) ; extra == "torch"
